pysintegrabanco/__init__.py
pysintegrabanco/banco_do_brasil.py
pysintegrabanco/santander.py
pysintegrabanco-0.0.4.dist-info/LICENSE
pysintegrabanco-0.0.4.dist-info/METADATA
pysintegrabanco-0.0.4.dist-info/WHEEL
pysintegrabanco-0.0.4.dist-info/top_level.txt
pysintegrabanco-0.0.4.dist-info/RECORD
